blyaml/__init__.py
blyaml/answers_to_yaml.py
blyaml/directory.py
blyaml/lists.py
blyaml/main.py
blyaml/questions.py
blyaml/text_formatting.py
blyaml/tree.py
blyaml/validators.py
blyaml-31.dist-info/LICENSE
blyaml-31.dist-info/METADATA
blyaml-31.dist-info/WHEEL
blyaml-31.dist-info/entry_points.txt
blyaml-31.dist-info/top_level.txt
blyaml-31.dist-info/RECORD
