Metadata-Version: 2.1
Name: blyaml
Version: 31
Summary: Tool for generating brainlabs.yaml files.
Home-page: https://github.com/Brainlabs-Digital/Brainlabs-YAML-Generator
Author: James Freeman
Author-email: james.f@brainlabsdigital.com
License: UNKNOWN
Platform: UNKNOWN
Requires-Dist: pyyaml (>=5.1.1)
Requires-Dist: pyinquirer
Requires-Dist: requests
